<?xml version="1.0" encoding="UTF-8" standalone="yes"?>
<root>

<name>freq()</name>

<category>Oscillator</category>

<subcategory></subcategory>

<usage>Web &amp; Application</usage>

<example>
<image></image>
<code><![CDATA[
import processing.sound.*;
SawOsc saw;

void setup() {
  size(640, 360);
  background(255);
    
  // Create square wave oscillator.
  saw = new SawOsc(this);
  saw.play();
  saw.freq(200);
}

void draw() {
}
]]></code>
</example>

<description><![CDATA[
Changes the frequency of the saw oscillator in Hz.
]]></description>

<syntax>
<c>saw</c>.freq(frequency)
</syntax>
	
<parameters>

</parameters>


<returns></returns>

<related></related>

<availability>1.0</availability>

<type>Method</type>

<partof>Library</partof>


</root>
