<?xml version="1.0" encoding="UTF-8" standalone="yes"?>
<root>
<name>text()</name>

<category>Typography</category>

<subcategory>Loading &amp; Displaying</subcategory>

<example>
<image>text_0.png</image>
<code><![CDATA[
PFont font;
// The font must be located in the sketch's 
// "data" directory to load successfully
font = loadFont("LetterGothicStd-32.vlw");
textFont(font);
text("word", 10, 30); 
fill(0, 102, 153);
text("word", 10, 60);
fill(0, 102, 153, 51);
text("word", 10, 90); 
]]></code>
</example>

<example>
<image>text_1.png</image>
<code><![CDATA[
size(100, 100, P3D);
PFont font;
font = loadFont("LetterGothicStd-32.vlw"); 
textFont(font); 
text("word", 15, 60, -30);  // Specify a z-axis value
fill(0, 102, 153);
text("word", 15, 60);  // Default depth, no z-value specified
]]></code>
</example>

<example>
<image>text_2.png</image>
<code><![CDATA[
PFont font;
font = loadFont("LetterGothicStd-Bold-12.vlw"); 
textFont(font); 
String s = "The quick brown fox jumped over the lazy dog.";
fill(50);
text(s, 10, 10, 70, 80);  // Text wraps within text box
]]></code>
</example>

<description><![CDATA[
Draws text to the screen. Displays the information specified in the <b>data</b> or <b>stringdata</b> parameters on the screen in the position specified by the <b>x</b> and <b>y</b> parameters and the optional <b>z</b> parameter. A default font will be used unless a font is set with the <b>textFont()</b> function. Change the color of the text with the <b>fill()</b> function. The text displays in relation to the <b>textAlign()</b> function, which gives the option to draw to the left, right, and center of the coordinates.
<br /><br />
The <b>x2</b> and <b>y2</b> parameters define a rectangular area to display within and may only be used with string data. For text drawn inside a rectangle, the coordinates are interpreted based on the current <b>rectMode()</b> setting.
]]></description>

</root>
